parrygg/__init__.py
parrygg/models/__init__.py
parrygg/models/bracket_pb2.py
parrygg/models/bracket_pb2_grpc.py
parrygg/models/entrant_pb2.py
parrygg/models/entrant_pb2_grpc.py
parrygg/models/event_export_pb2.py
parrygg/models/event_export_pb2_grpc.py
parrygg/models/event_pb2.py
parrygg/models/event_pb2_grpc.py
parrygg/models/filter_pb2.py
parrygg/models/filter_pb2_grpc.py
parrygg/models/game_pb2.py
parrygg/models/game_pb2_grpc.py
parrygg/models/group_pb2.py
parrygg/models/group_pb2_grpc.py
parrygg/models/hierarchy_pb2.py
parrygg/models/hierarchy_pb2_grpc.py
parrygg/models/image_pb2.py
parrygg/models/image_pb2_grpc.py
parrygg/models/notification_pb2.py
parrygg/models/notification_pb2_grpc.py
parrygg/models/pagination_pb2.py
parrygg/models/pagination_pb2_grpc.py
parrygg/models/phase_pb2.py
parrygg/models/phase_pb2_grpc.py
parrygg/models/progression_pb2.py
parrygg/models/progression_pb2_grpc.py
parrygg/models/request_pb2.py
parrygg/models/request_pb2_grpc.py
parrygg/models/slug_pb2.py
parrygg/models/slug_pb2_grpc.py
parrygg/models/tournament_pb2.py
parrygg/models/tournament_pb2_grpc.py
parrygg/models/user_pb2.py
parrygg/models/user_pb2_grpc.py
parrygg/services/__init__.py
parrygg/services/bracket_service_pb2.py
parrygg/services/bracket_service_pb2_grpc.py
parrygg/services/entrant_service_pb2.py
parrygg/services/entrant_service_pb2_grpc.py
parrygg/services/event_service_pb2.py
parrygg/services/event_service_pb2_grpc.py
parrygg/services/game_service_pb2.py
parrygg/services/game_service_pb2_grpc.py
parrygg/services/hierarchy_service_pb2.py
parrygg/services/hierarchy_service_pb2_grpc.py
parrygg/services/match_game_service_pb2.py
parrygg/services/match_game_service_pb2_grpc.py
parrygg/services/match_service_pb2.py
parrygg/services/match_service_pb2_grpc.py
parrygg/services/notification_service_pb2.py
parrygg/services/notification_service_pb2_grpc.py
parrygg/services/page_content_service_pb2.py
parrygg/services/page_content_service_pb2_grpc.py
parrygg-0.1.3.dist-info/LICENSE
parrygg-0.1.3.dist-info/METADATA
parrygg-0.1.3.dist-info/WHEEL
parrygg-0.1.3.dist-info/top_level.txt
parrygg-0.1.3.dist-info/RECORD
